converter/__init__.py
converter/scaleconverter.py
ScaleConvert-0.2.dist-info/METADATA
ScaleConvert-0.2.dist-info/WHEEL
ScaleConvert-0.2.dist-info/top_level.txt
ScaleConvert-0.2.dist-info/RECORD
