Metadata-Version: 2.1
Name: ScaleConvert
Version: 0.2
Summary: A Package to convert
Home-page: 
Author: Akash
Author-email: akash9129@gmail.com
Classifier: Programming Language :: Python :: 3
Classifier: License :: OSI Approved :: MIT License
Classifier: Operating System :: OS Independent
Requires-Python: >=3.6
